README.md
setup.cfg
setup.py
data/ephoto_xn2.dat
data/ephoto_xo.dat
data/ephoto_xo2.dat
data/snoem_eof.dat
data/ssflux_euvac.dat
data/ssflux_hint.dat
data/iri90/ccir11.asc
data/iri90/ccir12.asc
data/iri90/ccir13.asc
data/iri90/ccir14.asc
data/iri90/ccir15.asc
data/iri90/ccir16.asc
data/iri90/ccir17.asc
data/iri90/ccir18.asc
data/iri90/ccir19.asc
data/iri90/ccir20.asc
data/iri90/ccir21.asc
data/iri90/ccir22.asc
data/iri90/ursi11.asc
data/iri90/ursi12.asc
data/iri90/ursi13.asc
data/iri90/ursi14.asc
data/iri90/ursi15.asc
data/iri90/ursi16.asc
data/iri90/ursi17.asc
data/iri90/ursi18.asc
data/iri90/ursi19.asc
data/iri90/ursi20.asc
data/iri90/ursi21.asc
data/iri90/ursi22.asc
ncarglow/__init__.py
ncarglow/base.py
ncarglow/build.py
ncarglow/plots.py
ncarglow.egg-info/PKG-INFO
ncarglow.egg-info/SOURCES.txt
ncarglow.egg-info/dependency_links.txt
ncarglow.egg-info/entry_points.txt
ncarglow.egg-info/requires.txt
ncarglow.egg-info/top_level.txt