Metadata-Version: 2.1
Name: ncarglow
Version: 1.1.1
Summary: NCAR GLOW model
Home-page: https://github.com/scivision/ncar-glow
Author: Michael Hirsch, Ph.D.
License: UNKNOWN
Keywords: thermosphere,ionosphere
Platform: UNKNOWN
Classifier: Development Status :: 5 - Production/Stable
Classifier: Environment :: Console
Classifier: Intended Audience :: Science/Research
Classifier: Operating System :: OS Independent
Classifier: Programming Language :: Fortran
Classifier: Programming Language :: Python :: 3.6
Classifier: Programming Language :: Python :: 3.7
Classifier: Programming Language :: Python :: 3.8
Classifier: Topic :: Scientific/Engineering :: Atmospheric Science
Requires-Python: >= 3.6
Provides-Extra: cov
Provides-Extra: tests
Provides-Extra: plot
